qaravan/__init__.py
qaravan/algebraQ/__init__.py
qaravan/algebraQ/clifford_sim.py
qaravan/algebraQ/matchgate_sim.py
qaravan/applications/__init__.py
qaravan/applications/compilation.py
qaravan/applications/trotter.py
qaravan/core/__init__.py
qaravan/core/base_sim.py
qaravan/core/circuits.py
qaravan/core/gates.py
qaravan/core/hamiltonians.py
qaravan/core/lattices.py
qaravan/core/noise.py
qaravan/core/param_gates.py
qaravan/core/paulis.py
qaravan/core/utils.py
qaravan/tensorQ/__init__.py
qaravan/tensorQ/density_matrix_sim.py
qaravan/tensorQ/environments.py
qaravan/tensorQ/initializations.py
qaravan/tensorQ/monte_carlo_sim.py
qaravan/tensorQ/mpdo_sim.py
qaravan/tensorQ/mps_sim.py
qaravan/tensorQ/statevector_sim.py
qaravan/tensorQ/tn.py
qaravan-0.1.57.dist-info/licenses/LICENSE
qaravan-0.1.57.dist-info/METADATA
qaravan-0.1.57.dist-info/WHEEL
qaravan-0.1.57.dist-info/top_level.txt
qaravan-0.1.57.dist-info/RECORD
