Metadata-Version: 2.4
Name: qaravan
Version: 0.1.57
Summary: Unified classical simulation of noiseless and noisy quantum circuits
Author: Faisal Alam
Author-email: mfalam2@illinois.edu
Requires-Python: >=3.8
License-File: LICENSE
Requires-Dist: numpy<2.0,>=1.20
Requires-Dist: scipy<2.0,>=1.5.2
Requires-Dist: sympy>=1.6
Requires-Dist: matplotlib<4.0,>=3.7
Requires-Dist: tqdm>=4.67.1
Requires-Dist: ncon_torch>=0.3
Requires-Dist: torch>=1.12
Requires-Dist: stim>=1.14.0
Dynamic: author
Dynamic: author-email
Dynamic: license-file
Dynamic: requires-dist
Dynamic: requires-python
Dynamic: summary
